micropie.py
micropie-0.26.dist-info/licenses/LICENSE
micropie-0.26.dist-info/WHEEL
micropie-0.26.dist-info/METADATA
micropie-0.26.dist-info/RECORD
