Metadata-Version: 2.4
Name: micropie
Version: 0.26
Summary: An ultra micro ASGI web framework
Keywords: micropie,asgi,microframework,http
Author-email: Harrison Erd <harrisonerd@gmail.com>
Classifier: Framework :: AsyncIO
Classifier: Environment :: Web Environment
Classifier: Topic :: Internet :: WWW/HTTP
Classifier: Topic :: Internet :: WWW/HTTP :: WSGI
Classifier: Topic :: Software Development :: Libraries :: Application Frameworks
Classifier: Programming Language :: Python :: 3
Classifier: License :: OSI Approved :: BSD License
Classifier: Intended Audience :: Developers
Classifier: Operating System :: OS Independent
License-File: LICENSE
Requires-Dist: jinja2 ; extra == "all"
Requires-Dist: multipart ; extra == "all"
Requires-Dist: orjson ; extra == "all"
Requires-Dist: uvicorn ; extra == "all"
Requires-Dist: jinja2 ; extra == "standard"
Requires-Dist: multipart ; extra == "standard"
Project-URL: Homepage, https://patx.github.io/micropie
Project-URL: Repository, https://github.com/patx/micropie
Provides-Extra: all
Provides-Extra: standard
